trendvisdata/__init__.py
trendvisdata/chart_data.py
trendvisdata/chart_prep.py
trendvisdata/market_data.py
trendvisdata/sector_mappings.py
trendvisdata/trend.py
trendvisdata/trend_data.py
trendvisdata/trend_params.py
trendvisdata-1.1.4.dist-info/licenses/LICENSE
trendvisdata-1.1.4.dist-info/METADATA
trendvisdata-1.1.4.dist-info/WHEEL
trendvisdata-1.1.4.dist-info/top_level.txt
trendvisdata-1.1.4.dist-info/RECORD
