Metadata-Version: 2.4
Name: trendvisdata
Version: 1.1.4
Summary: Data extract and manipulation functions for Trend Visualizer library.
Home-page: https://github.com/GBERESEARCH/trendvisdata
Author: GBERESEARCH
Author-email: gberesearch@gmail.com
License: MIT
License-File: LICENSE
Requires-Dist: numpy>=1.24.1
Requires-Dist: requests>=2.28.1
Requires-Dist: pandas>=1.5.2
Requires-Dist: norgatedata>=1.0.64
Requires-Dist: yfinance>=0.2.40
Requires-Dist: technicalmethods>=0.2.4
Requires-Dist: lxml>=4.9.2
Dynamic: license-file
